{"channel_link":"","created_at":"2024-02-06T10:38:59.432799+00:00","created_by_user":{"attributes":{"email":"rojademo1@hotmail.com","handle":"rojademo1@hotmail.com","icon":"https://secure.gravatar.com/avatar/17da69a6a07e610caff9640dac0622ea?s=48&d=retro","name":"Shuan Shuan Chen","uuid":"398bbdde-c4a5-11ee-807d-828d79b953cd"},"id":"398bbdde-c4a5-11ee-807d-828d79b953cd","type":"users"},"incident_attributes":{"detection_method":{"type":"dropdown","value":"unknown"},"root_cause":{"type":"textbox","value":null},"services":{"type":"autocomplete","value":null},"severity":{"type":"dropdown","value":"SEV-2"},"state":{"type":"dropdown","value":"active"},"summary":{"type":"textbox","value":null},"teams":{"type":"autocomplete","value":null}},"incident_commander_user":{"attributes":{"email":"rojademo1@hotmail.com","handle":"rojademo1@hotmail.com","icon":"https://secure.gravatar.com/avatar/17da69a6a07e610caff9640dac0622ea?s=48&d=retro","name":"Shuan Shuan Chen","uuid":"398bbdde-c4a5-11ee-807d-828d79b953cd"},"id":"398bbdde-c4a5-11ee-807d-828d79b953cd","type":"users"},"last_modified_by_user":{"attributes":{"email":"rojademo1@hotmail.com","handle":"rojademo1@hotmail.com","icon":"https://secure.gravatar.com/avatar/17da69a6a07e610caff9640dac0622ea?s=48&d=retro","name":"Shuan Shuan Chen","uuid":"398bbdde-c4a5-11ee-807d-828d79b953cd"},"id":"398bbdde-c4a5-11ee-807d-828d79b953cd","type":"users"},"modified":"2024-02-06T10:38:59.432799+00:00","resolved":null,"severity":"SEV-2","state":"active","time_to_repair":0,"time_to_resolve":0,"title":"This is a test incident: CP4D auth service is not working","url":"https://app.datadoghq.com/incidents/22","video_call_link":""} 